{
  "sigs": {
    "unsigned long long fibonacci::RecursiveNaive(unsigned short)": "sig_0",
    "unsigned long long fibonacci::Iterative(unsigned short)": "sig_1",
    "unsigned long long fibonacci::LookupTable(unsigned short)": "sig_2"
  },
  "ctxs": {
    "sig_0": {
      "0": "path_0",
      "1": "path_0",
      "94": "path_2"
    },
    "sig_1": {
      "0": "path_0",
      "1": "path_0",
      "2": "path_1",
      "3": "path_2",
      "4": "path_3",
      "5": "path_4",
      "6": "path_5",
      "7": "path_6",
      "94": "path_7"
    },
    "sig_2": {
      "0": "path_0",
      "1": "path_0",
      "2": "path_0",
      "3": "path_0",
      "4": "path_0",
      "5": "path_0",
      "6": "path_0",
      "7": "path_0",
      "94": "path_1"
    }
  },
  "exprs": {
    "sig_0": {
      "path_0": "Symbol('C_F2106190_P0')",
      "path_2": "Symbol('C_F2106190_P2')"
    },
    "sig_1": {
      "path_0": "Symbol('C_F2110045_P0')",
      "path_1": "Add(Symbol('C_F2110045_P1'), Mul(Integer(3), Symbol('C_OP_ULL_ASSIGN')))",
      "path_2": "Add(Symbol('C_F2110045_P2'), Mul(Integer(6), Symbol('C_OP_ULL_ASSIGN')))",
      "path_3": "Add(Symbol('C_F2110045_P3'), Mul(Integer(9), Symbol('C_OP_ULL_ASSIGN')))",
      "path_4": "Add(Symbol('C_F2110045_P4'), Mul(Integer(12), Symbol('C_OP_ULL_ASSIGN')))",
      "path_5": "Add(Symbol('C_F2110045_P5'), Mul(Integer(15), Symbol('C_OP_ULL_ASSIGN')))",
      "path_6": "Add(Symbol('C_F2110045_P6'), Mul(Integer(18), Symbol('C_OP_ULL_ASSIGN')))",
      "path_7": "Symbol('C_F2110045_P7')"
    },
    "sig_2": {
      "path_0": "Symbol('C_F2110185_P0')",
      "path_1": "Symbol('C_F2110185_P1')"
    }
  }
}
